[{"title":"Solo Leveling","rating":9.9,"link":"https://www.mangago.me/read-manga/solo_leveling/"},{"title":"Suddenly Became a Princess One Day","rating":9.8,"link":"https://www.mangago.me/read-manga/suddenly_became_a_princess_one_day/"},{"title":"Mercenary Enrollment","rating":9.8,"link":"https://www.mangago.me/read-manga/mercenary_enrollment/"},{"title":"Omniscient Reader's Viewpoint","rating":9.8,"link":"https://www.mangago.me/read-manga/omniscient_reader_s_viewpoint/"},{"title":"I'll Be The Matriarch In This Life","rating":9.8,"link":"https://www.mangago.me/read-manga/i_ll_be_the_matriarch_in_this_life/"},{"title":"True Education","rating":9.8,"link":"https://www.mangago.me/read-manga/true_education/"},{"title":"See You In My 19th Life","rating":9.7,"link":"https://www.mangago.me/read-manga/please_take_care_of_me_in_this_life_as_well/"},{"title":"Trash of the Count's Family","rating":9.7,"link":"https://www.mangago.me/read-manga/trash_of_the_count_s_family/"},{"title":"Cool Doji Danshi","rating":9.7,"link":"https://www.mangago.me/read-manga/cool_doji_danshi/"},{"title":"I'm a Martial Art Villainess but I'm the Strongest!","rating":9.7,"link":"https://www.mangago.me/read-manga/i_m_a_martial_art_villainess_but_i_m_the_strongest/"},{"title":"Beware of the Villainess!","rating":9.7,"link":"https://www.mangago.me/read-manga/beware_of_the_villainess/"},{"title":"SSS-Class Suicide Hunter","rating":9.7,"link":"https://www.mangago.me/read-manga/sss_class_suicide_hunter/"},{"title":"The Way to Protect the Female Lead's Older Brother","rating":9.7,"link":"https://www.mangago.me/read-manga/the_way_to_protect_the_female_lead_s_older_brother/"},{"title":"Death Is The Only Ending For The Villainess","rating":9.7,"link":"https://www.mangago.me/read-manga/death_is_the_only_ending_for_the_villainess/"},{"title":"The Princess Imprints a Traitor","rating":9.7,"link":"https://www.mangago.me/read-manga/the_princess_imprints_a_traitor/"},{"title":"The Symbiotic Relationship Between the Rabbit and the Black Panther","rating":9.7,"link":"https://www.mangago.me/read-manga/the_symbiotic_relationship_between_the_rabbit_and_the_black_panther/"},{"title":"The Return of the Crazy Demon","rating":9.7,"link":"https://www.mangago.me/read-manga/the_return_of_the_crazy_demon/"},{"title":"I Became the Male Lead’s Adopted Daughter","rating":9.7,"link":"https://www.mangago.me/read-manga/i_became_the_male_lead_s_adopted_daughter/"},{"title":"Leveling Up, By Only Eating!","rating":9.6,"link":"https://www.mangago.me/read-manga/levelling_up_by_only_eating/"},{"title":"Shadow House","rating":9.6,"link":"https://www.mangago.me/read-manga/shadow_house/"},{"title":"The Evil Lady's Hero","rating":9.6,"link":"https://www.mangago.me/read-manga/the_evil_lady_s_hero/"},{"title":"The Lady and the Beast","rating":9.6,"link":"https://www.mangago.me/read-manga/the_lady_and_the_beast/"},{"title":"Inso's Law Webtoon","rating":9.6,"link":"https://www.mangago.me/read-manga/inso_s_law/"},{"title":"I Want to Be You, Just For A Day Webtoon","rating":9.6,"link":"https://www.mangago.me/read-manga/i_want_to_be_you_just_for_a_day/"},{"title":"I Became the Hero's Mom","rating":9.6,"link":"https://www.mangago.me/read-manga/i_became_the_hero_s_mom/"},{"title":"I Raised the Beast Well","rating":9.6,"link":"https://www.mangago.me/read-manga/i_raised_the_beast_well/"},{"title":"The Villainess is a Marionette","rating":9.6,"link":"https://www.mangago.me/read-manga/the_villainess_is_a_marionette/"},{"title":"I’ll Just Live on as a Villainess","rating":9.6,"link":"https://www.mangago.me/read-manga/i_ll_just_live_on_as_a_villainess/"},{"title":"Father, I don't Want this Marriage","rating":9.6,"link":"https://www.mangago.me/read-manga/father_i_don_t_want_to_get_married/"},{"title":"Untouchable Lady","rating":9.6,"link":"https://www.mangago.me/read-manga/untouchable_lady/"},{"title":"Merry Go Round","rating":9.6,"link":"https://www.mangago.me/read-manga/merry_go_round_1/"},{"title":"Please have a meal","rating":9.6,"link":"https://www.mangago.me/read-manga/please_have_a_meal/"},{"title":"Return to Player","rating":9.6,"link":"https://www.mangago.me/read-manga/return_to_player/"},{"title":"I Became the Wife of the Male Lead","rating":9.6,"link":"https://www.mangago.me/read-manga/i_became_the_wife_of_the_male_lead_bored_corona_kids_version/"},{"title":"Doctor’s Rebirth","rating":9.6,"link":"https://www.mangago.me/read-manga/doctor_s_rebirth/"},{"title":"Murim Login","rating":9.6,"link":"https://www.mangago.me/read-manga/murim_login/"},{"title":"Kill the Hero","rating":9.5,"link":"https://www.mangago.me/read-manga/kill_the_hero/"},{"title":"I Stole The Male Lead's First Night","rating":9.5,"link":"https://www.mangago.me/read-manga/i_stole_the_male_lead_s_first_night/"},{"title":"When the Villainess Loves","rating":9.5,"link":"https://www.mangago.me/read-manga/when_the_villainess_loves/"},{"title":"Queen Cecia's Shorts","rating":9.5,"link":"https://www.mangago.me/read-manga/queen_cecia_s_shorts/"},{"title":"Actually, I was the Real One","rating":9.5,"link":"https://www.mangago.me/read-manga/actually_i_was_the_real_one/"},{"title":"Homework of the Mind","rating":9.5,"link":"https://www.mangago.me/read-manga/homework_of_the_mind/"},{"title":"The Viridescent Crown","rating":9.5,"link":"https://www.mangago.me/read-manga/recording_hall/"},{"title":"The Princess in the Dumpster","rating":9.5,"link":"https://www.mangago.me/read-manga/the_princess_in_the_dumpster/"},{"title":"I'm A Stepmother, But My Daughter Is Just Too Cute!","rating":9.5,"link":"https://www.mangago.me/read-manga/i_m_a_stepmother_but_my_daughter_is_just_too_cute/"},{"title":"A Hunter's Courtship Method","rating":9.5,"link":"https://www.mangago.me/read-manga/a_hunter_s_courtship_method/"},{"title":"Please Throw Me Away","rating":9.5,"link":"https://www.mangago.me/read-manga/please_throw_me_away/"},{"title":"I Shall Live As a Prince","rating":9.5,"link":"https://www.mangago.me/read-manga/i_shall_live_as_a_prince/"},{"title":"Say Ah, the Golden Spoon is Entering","rating":9.5,"link":"https://www.mangago.me/read-manga/say_ah_the_golden_spoon_is_entering_3_dumb_musketeers/"},{"title":"Carrier Falcon Princess","rating":9.5,"link":"https://www.mangago.me/read-manga/cavier_falcon_princess/"},{"title":"You're All Dead if You Mess With My Brother","rating":9.5,"link":"https://www.mangago.me/read-manga/if_you_touch_my_brother_you_re_all_dead/"},{"title":"A Red Knight Does Not Blindly Follow Money","rating":9.5,"link":"https://www.mangago.me/read-manga/a_true_knight_does_not_blindly_follow_money/"},{"title":"Yeon Lok Heun","rating":9.5,"link":"https://www.mangago.me/read-manga/yeon_lok_heun/"},{"title":"Today the Villainess has Fun Again","rating":9.5,"link":"https://www.mangago.me/read-manga/today_the_villainess_has_fun_again/"},{"title":"Ygret","rating":9.5,"link":"https://www.mangago.me/read-manga/ygret/"},{"title":"The lazy prince becomes a genius","rating":9.5,"link":"https://www.mangago.me/read-manga/the_lazy_prince_becomes_a_genius/"},{"title":"Honey, I'm Going on Strike","rating":9.5,"link":"https://www.mangago.me/read-manga/honey_i_m_going_on_strike/"},{"title":"Shadow Queen","rating":9.4,"link":"https://www.mangago.me/read-manga/shadow_queen/"},{"title":"It Looks Like I’ve Fallen into the World of a Reverse Harem Game","rating":9.4,"link":"https://www.mangago.me/read-manga/it_looks_like_i_ve_fallen_into_the_world_of_a_reverse_harem_game/"},{"title":"For Better or For Worse","rating":9.4,"link":"https://www.mangago.me/read-manga/is_it_a_fortune_or_is_it_a_woe/"},{"title":"The Scholar's Reincarnation","rating":9.4,"link":"https://www.mangago.me/read-manga/the_scholars_reincarnation/"},{"title":"The Undefeatable Swordsman","rating":9.4,"link":"https://www.mangago.me/read-manga/the_undefeatable_swordsman/"},{"title":"THE VIRGIN WITCH","rating":9.4,"link":"https://www.mangago.me/read-manga/the_virgin_witch/"},{"title":"The Lady's Butler","rating":9.4,"link":"https://www.mangago.me/read-manga/the_lady_s_butler/"},{"title":"Anyone Can Become a Villainess","rating":9.4,"link":"https://www.mangago.me/read-manga/anyone_can_become_a_villainess/"},{"title":"She's My Type","rating":9.4,"link":"https://www.mangago.me/read-manga/she_s_my_type/"},{"title":"I Became the Tyrant's Secretary","rating":9.4,"link":"https://www.mangago.me/read-manga/i_became_the_tyrant_s_secretary/"},{"title":"I'm Stanning the Prince","rating":9.4,"link":"https://www.mangago.me/read-manga/i_m_stanning_the_prince/"},{"title":"Cinderella Wasn't Me","rating":9.4,"link":"https://www.mangago.me/read-manga/cinderella_wasn_t_me/"},{"title":"In This Life, I Will Raise You Well, Your Majesty!","rating":9.4,"link":"https://www.mangago.me/read-manga/in_this_life_i_will_raise_you_well_your_majesty/"},{"title":"The couple breaker","rating":9.4,"link":"https://www.mangago.me/read-manga/the_couple_breaker/"},{"title":"The Flower Dances and the Wind Sings","rating":9.3,"link":"https://www.mangago.me/read-manga/the_flower_dance_and_the_wind_song/"},{"title":"The Blood Of Madam Giselle","rating":9.3,"link":"https://www.mangago.me/read-manga/the_blood_of_madam_giselle/"},{"title":"Rendezvous","rating":9.3,"link":"https://www.mangago.me/read-manga/rendezvous/"},{"title":"The Way That Knight Lives As a Lady","rating":9.3,"link":"https://www.mangago.me/read-manga/the_way_that_knight_lives_as_a_lady/"},{"title":"Follow The Bread Crumbs","rating":9.3,"link":"https://www.mangago.me/read-manga/follow_the_bread_crumbs/"},{"title":"The Princess Pretends to Be Crazy","rating":9.3,"link":"https://www.mangago.me/read-manga/the_princess_pretends_to_be_crazy/"},{"title":"No Longer A Heroine!","rating":9.3,"link":"https://www.mangago.me/read-manga/no_longer_a_heroine/"},{"title":"Let’s Hide My Younger Brother First","rating":9.3,"link":"https://www.mangago.me/read-manga/let_s_hide_my_younger_brother_first/"},{"title":"The Villainess Needs A Tyrant","rating":9.2,"link":"https://www.mangago.me/read-manga/the_villainess_needs_a_tyrant/"},{"title":"The Emperor Reverses Time","rating":9.2,"link":"https://www.mangago.me/read-manga/the_emperor_reverses_time/"},{"title":"Revenge Wedding","rating":9.1,"link":"https://www.mangago.me/read-manga/revenge_wedding/"},{"title":"Why She Lives as a Villainess","rating":9.1,"link":"https://www.mangago.me/read-manga/why_she_lives_as_a_villainess/"},{"title":"The Investigator of Mueller","rating":9.1,"link":"https://www.mangago.me/read-manga/the_investigator_of_mueller/"},{"title":"Leveling My Husband to the Max","rating":9.1,"link":"https://www.mangago.me/read-manga/leveling_my_husband_to_the_max/"},{"title":"I Want to Become a Heroic Swordswoman! Webtoon","rating":9,"link":"https://www.mangago.me/read-manga/i_want_to_become_a_heroic_swordswoman/"},{"title":"I'll Save this Damn Family!","rating":9,"link":"https://www.mangago.me/read-manga/i_ll_save_a_decent_family/"},{"title":"Nulliitas: The Half-Blood Royalty","rating":9,"link":"https://www.mangago.me/read-manga/nulliitas_the_half_blood_royalty/"},{"title":"Save Me, Princess","rating":8.9,"link":"https://www.mangago.me/read-manga/save_me_princess/"}]