[{"title":"IF Future","rating":9.1,"link":"https://www.mangago.me/read-manga/if_future/"},{"title":"JK's Tragic Isekai Reincarnation as the Villainess ~But My Precious Side Character!","rating":7.8,"link":"https://www.mangago.me/read-manga/jk_s_tragic_isekai_reincarnation_as_the_villainess_but_my_precious_side_character/"},{"title":"Lady Elisha's Erotica","rating":9.3,"link":"https://www.mangago.me/read-manga/lady_elisha_s_erotica/"},{"title":"Master has chosen my husband candidates","rating":8.9,"link":"https://www.mangago.me/read-manga/master_has_chosen_my_husband_candidates/"},{"title":"Prince Snow White is Taken by the Queen","rating":9,"link":"https://www.mangago.me/read-manga/prince_snow_white_is_taken_by_the_queen/"},{"title":"Evangeline","rating":9,"link":"https://www.mangago.me/read-manga/evangeline/"},{"title":"I Found a Husband When I Picked Up the Male Lead","rating":9.5,"link":"https://www.mangago.me/read-manga/i_found_a_husband_when_i_picked_up_the_male_lead/"},{"title":"I Wont Accept Your Regrets","rating":9,"link":"https://www.mangago.me/read-manga/i_wont_accept_your_regrets_shio/"},{"title":"Secret X Folder","rating":9,"link":"https://www.mangago.me/read-manga/secret_x_folder/"},{"title":"Learning to Love You","rating":9.2,"link":"https://www.mangago.me/read-manga/learning_to_love_you/"},{"title":"The Man Who Saved Me on my Isekai Trip is a Killer","rating":7.5,"link":"https://www.mangago.me/read-manga/the_man_who_saved_me_on_my_isekai_trip_is_a_killer/"},{"title":"The Duchess' Lewd Invitation","rating":8.8,"link":"https://www.mangago.me/read-manga/the_duchess_lewd_invitation/"},{"title":"Your Majesty Is Mine","rating":8.8,"link":"https://www.mangago.me/read-manga/your_majesty_is_mine/"},{"title":"Zombie Girlfriend!","rating":9.1,"link":"https://www.mangago.me/read-manga/zombie_girlfriend/"},{"title":"THE VIRGIN WITCH","rating":9.4,"link":"https://www.mangago.me/read-manga/the_virgin_witch/"},{"title":"Erotic Scheme","rating":8.5,"link":"https://www.mangago.me/read-manga/erotic_scheme/"}]