[{"title":"Hatsujou Suru Unmei ~Eriito Alpha No Risei Ga Genkai~","rating":9.1,"link":"https://www.mangago.me/read-manga/hatsujou_suru_unmei_eriito_alpha_no_risei_ga_genkai/"},{"title":"Gokudou to Omega ~Mukidashi no Katsuai.~","rating":9,"link":"https://www.mangago.me/read-manga/gokudou_to_omega_mukidashi_no_katsuai/"},{"title":"Hide & Seek","rating":8.1,"link":"https://www.mangago.me/read-manga/hide_seek/"},{"title":"Eri and Her Older Brother on a Certain Day","rating":7.4,"link":"https://www.mangago.me/read-manga/eri_and_her_older_brother_on_a_certain_day/"},{"title":"A Wish's Conclusion","rating":7.9,"link":"https://www.mangago.me/read-manga/a_wish_s_conclusion/"},{"title":"Heian Juukon Monogatari: Juujin Danna-sama wa Shojo Hanayome wo Amaku Torokasu","rating":8.4,"link":"https://www.mangago.me/read-manga/heian_juukon_monogatari_juujin_danna_sama_wa_shojo_hanayome_wo_amaku_torokasu/"},{"title":"Devil Lolita","rating":6.9,"link":"https://www.mangago.me/read-manga/devil_lolita/"},{"title":"When You Sleep","rating":7.5,"link":"https://www.mangago.me/read-manga/when_you_sleep/"},{"title":"Seikoui wo Zentei to Shitaosasoidesu ka? ~Nikushoku Narcissist to Zettai Renai shinai Joshi~","rating":8.6,"link":"https://www.mangago.me/read-manga/seikoui_wo_zentei_to_shitaosasoidesu_ka_nikushoku_narcissist_to_zettai_renai_shinai_joshi/"},{"title":"Arabian Halloween Night","rating":8.2,"link":"https://www.mangago.me/read-manga/arabian_halloween_night/"},{"title":"197x","rating":6.8,"link":"https://www.mangago.me/read-manga/197x/"},{"title":"Blush-DC.","rating":7.8,"link":"https://www.mangago.me/read-manga/blush_dc/"},{"title":"Virgin Chauwa!","rating":8.7,"link":"https://www.mangago.me/read-manga/virgin_chauwa/"},{"title":"Your Majesty Is Mine","rating":8.8,"link":"https://www.mangago.me/read-manga/your_majesty_is_mine/"},{"title":"Ore Wa Tsuma ni Mainichi Maiban Oboretai","rating":9.1,"link":"https://www.mangago.me/read-manga/ore_wa_tsuma_ni_mainichi_maiban_oboretai/"},{"title":"Sundere!","rating":6.6,"link":"https://www.mangago.me/read-manga/sundere/"},{"title":"Dornroschen","rating":7.3,"link":"https://www.mangago.me/read-manga/dornroschen/"},{"title":"Super Streaming! Turning My Stepmom into My Cumdump!","rating":7.2,"link":"https://www.mangago.me/read-manga/super_streaming_turning_my_stepmom_into_my_cumdump/"},{"title":"Aki-sora","rating":7.1,"link":"https://www.mangago.me/read-manga/aki_sora/"},{"title":"The Man Who Saved Me on my Isekai Trip is a Killer","rating":7.5,"link":"https://www.mangago.me/read-manga/the_man_who_saved_me_on_my_isekai_trip_is_a_killer/"},{"title":"Where Are You Running off To","rating":9.1,"link":"https://www.mangago.me/read-manga/where_are_you_running_off_to/"},{"title":"Professor Lock’s Strange Lab","rating":6.3,"link":"https://www.mangago.me/read-manga/professor_lock_s_strange_lab/"},{"title":"Animal Girl Hotline ~ Bird Girl Rupia","rating":7.6,"link":"https://www.mangago.me/read-manga/animal_girl_hotline_bird_girl_rupia/"},{"title":"The Idolm@ster - Cinderella Girls Dj - Nao-chan To Asedaku De Suru Hon","rating":7.5,"link":"https://www.mangago.me/read-manga/the_idolm_ster_cinderella_girls_dj_nao_chan_to_asedaku_de_suru_hon/"},{"title":"Before Dawn","rating":6,"link":"https://www.mangago.me/read-manga/before_dawn/"},{"title":"Reikoku Shitsuji wa Maid wo Dekiai suru","rating":8.7,"link":"https://www.mangago.me/read-manga/reikoku_shitsuji_wa_maid_wo_dekiai_suru/"},{"title":"Tsuna-chan no Shitsuji","rating":5.1,"link":"https://www.mangago.me/read-manga/tsuna_chan_no_shitsuji_katekyo_hitman_reborn/"},{"title":"The Other World's Wizard Does Not Chant","rating":8.2,"link":"https://www.mangago.me/read-manga/the_other_world_s_wizard_does_not_chant/"},{"title":"The Mad Prince's Distorted Love Prisoner ~ A Genderbent Knight","rating":7.1,"link":"https://www.mangago.me/read-manga/the_mad_prince_s_distorted_love_prisoner_a_genderbent_knight/"},{"title":"Singing About Love Falls Asleep With Our Song","rating":7,"link":"https://www.mangago.me/read-manga/singing_about_love_falls_asleep_with_our_song_uta_no_prince_sama/"},{"title":"The Siren's Cradle","rating":8.8,"link":"https://www.mangago.me/read-manga/the_siren_s_cradle_sadistic_scanlations/"},{"title":"Shinsou no Hanayome","rating":7.7,"link":"https://www.mangago.me/read-manga/shinsou_no_hanayome/"},{"title":"False Flower","rating":7.3,"link":"https://www.mangago.me/read-manga/false_flower/"},{"title":"Jichou shinai Motoyuusha no Tsuyokute Tanoshii New Game","rating":8.1,"link":"https://www.mangago.me/read-manga/jichou_shinai_motoyuusha_no_tsuyokute_tanoshii_new_game/"},{"title":"Traditional Job of Washing Girls' Body Webtoon","rating":7.7,"link":"https://www.mangago.me/read-manga/traditional_job_of_washing_girls_body/"},{"title":"Yandere Ouji ga Shachiku Onna no Watashi o Hanasanai","rating":8.4,"link":"https://www.mangago.me/read-manga/yandere_ouji_ga_shachiku_onna_no_watashi_o_hanasanai/"},{"title":"Kyuuketsuki no Inshitsuai","rating":8.5,"link":"https://www.mangago.me/read-manga/kyuuketsuki_no_inshitsuai/"},{"title":"Over-cumming writer’s block","rating":9.3,"link":"https://www.mangago.me/read-manga/over_cumming_writer_s_block/"},{"title":"Sono Keisatsukan, Tokidoki Yajuu!","rating":9,"link":"https://www.mangago.me/read-manga/sono_keisatsukan_tokidoki_yajuu/"},{"title":"Re:Hatsukoi","rating":8,"link":"https://www.mangago.me/read-manga/re_hatsukoi/"},{"title":"closet","rating":6.3,"link":"https://www.mangago.me/read-manga/closet/"},{"title":"Childhood Friends With Benefits","rating":7.3,"link":"https://www.mangago.me/read-manga/childhood_friends_with_benefits/"},{"title":"Kyuusen no Shima","rating":6.3,"link":"https://www.mangago.me/read-manga/kyuusen_no_shima/"},{"title":"Ore Shucchouchuu, Tsuma Netorarechuu. (Digital)","rating":6.2,"link":"https://www.mangago.me/read-manga/ore_shucchouchuu_tsuma_netorarechuu_digital/"},{"title":"Cartoonists NSFW Webtoon","rating":8.4,"link":"https://www.mangago.me/read-manga/cartoonists_nsfw/"},{"title":"Ijimerare - The three owners of mine and my \"woman\" self","rating":6.6,"link":"https://www.mangago.me/read-manga/ijimerare_the_three_owners_of_mine_and_my_woman_self/"},{"title":"Lady K and the Sick man","rating":9.4,"link":"https://www.mangago.me/read-manga/lady_k_and_the_sick_man/"},{"title":"The Strongest Knightess Cannot Escape An Obsessive Prince!","rating":8.1,"link":"https://www.mangago.me/read-manga/the_strongest_knightess_cannot_escape_an_obsessive_prince/"},{"title":"JK's Tragic Isekai Reincarnation as the Villainess ~But My Precious Side Character!","rating":7.8,"link":"https://www.mangago.me/read-manga/jk_s_tragic_isekai_reincarnation_as_the_villainess_but_my_precious_side_character/"},{"title":"Tsukiyo no Midare Zake","rating":7.2,"link":"https://www.mangago.me/read-manga/tsukiyo_no_midare_zake/"},{"title":"The col-hearted prince may have the potential for doting","rating":8,"link":"https://www.mangago.me/read-manga/the_col_hearted_prince_may_have_the_potential_for_doting/"},{"title":"38℃ Loveberry Twins","rating":7.8,"link":"https://www.mangago.me/read-manga/38_loveberry_twins/"},{"title":"Secret Mating Rituals of the Jungle Dwelling Dog-like Indigenous Men","rating":9,"link":"https://www.mangago.me/read-manga/secret_mating_rituals_of_the_jungle_dwelling_dog_like_indigenous_men/"},{"title":"Shojo Kon ~Kohinata Fuufu wa Shite Mitai~","rating":9.4,"link":"https://www.mangago.me/read-manga/shojo_kon_kohinata_fuufu_wa_shite_mitai/"},{"title":"O Kuchi ga Etchina Jakuten Datte, Raibaru no Eriito Douryou ni Barete Shimaimashita","rating":9,"link":"https://www.mangago.me/read-manga/o_kuchi_ga_etchina_jakuten_datte_raibaru_no_eriito_douryou_ni_barete_shimaimashita/"}]