[{"title":"Eleceed","rating":9.9,"link":"https://www.mangago.me/read-manga/eleceed/"},{"title":"Mercenary Enrollment","rating":9.8,"link":"https://www.mangago.me/read-manga/mercenary_enrollment/"},{"title":"I'll Be The Matriarch In This Life","rating":9.8,"link":"https://www.mangago.me/read-manga/i_ll_be_the_matriarch_in_this_life/"},{"title":"Wind Breaker","rating":9.8,"link":"https://www.mangago.me/read-manga/wind_breaker/"},{"title":"Omniscient Reader's Viewpoint","rating":9.8,"link":"https://www.mangago.me/read-manga/omniscient_reader_s_viewpoint/"},{"title":"The S-Classes That I Raised","rating":9.8,"link":"https://www.mangago.me/read-manga/the_s_classes_that_i_raised/"},{"title":"Positively Yours","rating":9.7,"link":"https://www.mangago.me/read-manga/positively_yours/"},{"title":"Beware of the Villainess!","rating":9.7,"link":"https://www.mangago.me/read-manga/beware_of_the_villainess/"},{"title":"Remarried Empress","rating":9.7,"link":"https://www.mangago.me/read-manga/remarried_empress/"},{"title":"The Symbiotic Relationship Between the Rabbit and the Black Panther","rating":9.7,"link":"https://www.mangago.me/read-manga/the_symbiotic_relationship_between_the_rabbit_and_the_black_panther/"},{"title":"The Princess Imprints a Traitor","rating":9.7,"link":"https://www.mangago.me/read-manga/the_princess_imprints_a_traitor/"},{"title":"Death Is The Only Ending For The Villainess","rating":9.7,"link":"https://www.mangago.me/read-manga/death_is_the_only_ending_for_the_villainess/"},{"title":"I Became the Male Lead’s Adopted Daughter","rating":9.7,"link":"https://www.mangago.me/read-manga/i_became_the_male_lead_s_adopted_daughter/"},{"title":"Ranker who lives a second time","rating":9.7,"link":"https://www.mangago.me/read-manga/ranker_who_lives_a_second_time/"},{"title":"SSS-Class Suicide Hunter","rating":9.7,"link":"https://www.mangago.me/read-manga/sss_class_suicide_hunter/"},{"title":"Trash of the Count's Family","rating":9.7,"link":"https://www.mangago.me/read-manga/trash_of_the_count_s_family/"},{"title":"Lookism","rating":9.7,"link":"https://www.mangago.me/read-manga/lookism/"},{"title":"Weak Hero","rating":9.7,"link":"https://www.mangago.me/read-manga/weak_hero/"},{"title":"Seasons of Blossom","rating":9.7,"link":"https://www.mangago.me/read-manga/seasons_of_blossom/"},{"title":"Noblesse","rating":9.7,"link":"https://www.mangago.me/read-manga/noblesse/"},{"title":"See You In My 19th Life","rating":9.7,"link":"https://www.mangago.me/read-manga/please_take_care_of_me_in_this_life_as_well/"},{"title":"Under the Oak Tree","rating":9.6,"link":"https://www.mangago.me/read-manga/under_the_oak_tree/"},{"title":"Father, I don't Want this Marriage","rating":9.6,"link":"https://www.mangago.me/read-manga/father_i_don_t_want_to_get_married/"},{"title":"Inso's Law Webtoon","rating":9.6,"link":"https://www.mangago.me/read-manga/inso_s_law/"},{"title":"I Want to Be You, Just For A Day Webtoon","rating":9.6,"link":"https://www.mangago.me/read-manga/i_want_to_be_you_just_for_a_day/"},{"title":"The Villainess Reverses the Hourglass","rating":9.6,"link":"https://www.mangago.me/read-manga/the_villainess_reverses_the_hourglass/"},{"title":"A Stepmother's Märchen","rating":9.6,"link":"https://www.mangago.me/read-manga/a_stepmother_s_m_rchen/"},{"title":"I’ll Just Live on as a Villainess","rating":9.6,"link":"https://www.mangago.me/read-manga/i_ll_just_live_on_as_a_villainess/"},{"title":"I Raised the Beast Well","rating":9.6,"link":"https://www.mangago.me/read-manga/i_raised_the_beast_well/"},{"title":"The Monster Duchess and Contract Princess","rating":9.6,"link":"https://www.mangago.me/read-manga/the_monster_duchess_and_contract_princess/"},{"title":"Untouchable Lady","rating":9.6,"link":"https://www.mangago.me/read-manga/untouchable_lady/"},{"title":"The Reason Why Raeliana Ended up at the Duke's Mansion","rating":9.6,"link":"https://www.mangago.me/read-manga/the_reason_why_raeliana_ended_up_at_the_duke_s_mansion/"},{"title":"The Lord of Sun","rating":9.6,"link":"https://www.mangago.me/read-manga/the_lord_of_sun/"},{"title":"The Boxer","rating":9.6,"link":"https://www.mangago.me/read-manga/the_boxer/"},{"title":"Legend of the Northern Blade","rating":9.6,"link":"https://www.mangago.me/read-manga/legend_of_the_northern_blade/"},{"title":"Hidden Love: Can","rating":9.6,"link":"https://www.mangago.me/read-manga/hidden_love_can_t_be_concealed/"},{"title":"Three Lifetimes","rating":9.6,"link":"https://www.mangago.me/read-manga/three_lifetimes/"},{"title":"Olgami","rating":9.6,"link":"https://www.mangago.me/read-manga/olgami/"},{"title":"Ellin's Solhwa","rating":9.6,"link":"https://www.mangago.me/read-manga/ellin_s_solhwa/"},{"title":"The World After The Fall","rating":9.6,"link":"https://www.mangago.me/read-manga/the_world_after_the_fall/"},{"title":"This Is An Obvious Fraudulent Marriage Webtoon","rating":9.5,"link":"https://www.mangago.me/read-manga/this_is_an_obvious_fraudulent_marriage/"},{"title":"Oh! Holy","rating":9.5,"link":"https://www.mangago.me/read-manga/oh_lord_jesus/"},{"title":"When the Villainess Loves","rating":9.5,"link":"https://www.mangago.me/read-manga/when_the_villainess_loves/"},{"title":"My Husband Hides His Beauty","rating":9.5,"link":"https://www.mangago.me/read-manga/my_husband_hides_his_beauty/"},{"title":"Actually, I was the Real One","rating":9.5,"link":"https://www.mangago.me/read-manga/actually_i_was_the_real_one/"},{"title":"The Lady I Served Became a Young Master","rating":9.5,"link":"https://www.mangago.me/read-manga/the_lady_i_served_became_a_young_master/"},{"title":"Uncle Cool","rating":9.5,"link":"https://www.mangago.me/read-manga/uncle_cool/"},{"title":"Carrier Falcon Princess","rating":9.5,"link":"https://www.mangago.me/read-manga/cavier_falcon_princess/"},{"title":"I Became the Wife of the Monstrous Crown Prince","rating":9.5,"link":"https://www.mangago.me/read-manga/i_became_the_wife_of_the_monstrous_crown_prince/"},{"title":"Survive as the Hero's Wife","rating":9.5,"link":"https://www.mangago.me/read-manga/survive_as_the_hero_s_wife/"},{"title":"The Viridescent Crown","rating":9.5,"link":"https://www.mangago.me/read-manga/recording_hall/"},{"title":"Bloody Romance","rating":9.5,"link":"https://www.mangago.me/read-manga/bloody_romance/"},{"title":"Three Brothers","rating":9.5,"link":"https://www.mangago.me/read-manga/three_brothers/"},{"title":"The God of High School","rating":9.5,"link":"https://www.mangago.me/read-manga/the_god_of_high_school/"},{"title":"My Butler, Not Lover","rating":9.5,"link":"https://www.mangago.me/read-manga/my_butler_not_lover/"},{"title":"Doctor Elise","rating":9.5,"link":"https://www.mangago.me/read-manga/doctor_elise/"},{"title":"The Office Blind Date","rating":9.5,"link":"https://www.mangago.me/read-manga/the_office_blind_date/"},{"title":"Empress Hunt","rating":9.5,"link":"https://www.mangago.me/read-manga/empress_hunt/"},{"title":"My Reason to Die","rating":9.5,"link":"https://www.mangago.me/read-manga/my_reason_to_die/"},{"title":"Pure Love Operation","rating":9.5,"link":"https://www.mangago.me/read-manga/pure_love_operation/"},{"title":"I Stole The Male Lead's First Night","rating":9.5,"link":"https://www.mangago.me/read-manga/i_stole_the_male_lead_s_first_night/"},{"title":"Safe as Houses","rating":9.5,"link":"https://www.mangago.me/read-manga/safe_as_houses/"},{"title":"Lovely Again Today","rating":9.5,"link":"https://www.mangago.me/read-manga/lovely_again_today/"},{"title":"I Tamed a Tyrant and Ran Away","rating":9.5,"link":"https://www.mangago.me/read-manga/i_tamed_a_tyrant_and_ran_away/"},{"title":"The Broken Ring : This Marriage Will Fail Anyway","rating":9.5,"link":"https://www.mangago.me/read-manga/the_broken_ring_this_marriage_will_fail_anyway/"},{"title":"Bloody Sweet","rating":9.4,"link":"https://www.mangago.me/read-manga/honey_blood_lee_narae/"},{"title":"Shadow Queen","rating":9.4,"link":"https://www.mangago.me/read-manga/shadow_queen/"},{"title":"Highschool Lunch Dad","rating":9.4,"link":"https://www.mangago.me/read-manga/highschool_lunch_dad/"},{"title":"The Villainess Lives Twice","rating":9.4,"link":"https://www.mangago.me/read-manga/the_villainess_lives_twice/"},{"title":"The Tyrant's Only Perfumer","rating":9.4,"link":"https://www.mangago.me/read-manga/the_tyrant_s_only_perfumer/"},{"title":"Shadow Beauty","rating":9.4,"link":"https://www.mangago.me/read-manga/shadow_beauty/"},{"title":"The Lady and Her Butler","rating":9.4,"link":"https://www.mangago.me/read-manga/the_lady_and_her_butler/"},{"title":"Mystic Messenger","rating":9.4,"link":"https://www.mangago.me/read-manga/mystic_messenger/"},{"title":"My In-laws are Obsessed With Me","rating":9.4,"link":"https://www.mangago.me/read-manga/my_in_laws_are_obsessed_with_me/"},{"title":"Beatrice","rating":9.4,"link":"https://www.mangago.me/read-manga/beatrice/"},{"title":"The Beast Tamed by the Villainess","rating":9.4,"link":"https://www.mangago.me/read-manga/the_beast_tamed_by_the_villainess/"},{"title":"When You're Targeted by the Bully","rating":9.3,"link":"https://www.mangago.me/read-manga/when_you_re_targeted_by_the_bully/"},{"title":"Daisy(Lisabel)","rating":9.3,"link":"https://www.mangago.me/read-manga/daisy_lisabel/"},{"title":"Sincerely: i Became a Duke’s Maid","rating":9.3,"link":"https://www.mangago.me/read-manga/sincerely_i_became_a_duke_s_maid/"},{"title":"I am a child of this house","rating":9.3,"link":"https://www.mangago.me/read-manga/i_am_a_child_of_this_house/"},{"title":"Let’s Hide My Younger Brother First","rating":9.3,"link":"https://www.mangago.me/read-manga/let_s_hide_my_younger_brother_first/"},{"title":"Failed To Abandon The Villain","rating":9.3,"link":"https://www.mangago.me/read-manga/failed_to_abandon_the_villain/"},{"title":"Leylin Of Turin","rating":9.3,"link":"https://www.mangago.me/read-manga/leylin_of_turin/"},{"title":"The Real Daughter is Back","rating":9.3,"link":"https://www.mangago.me/read-manga/the_real_daughter_is_back/"},{"title":"Undercover! Chaebol High School","rating":9.3,"link":"https://www.mangago.me/read-manga/undercover_chaebol_high_school/"},{"title":"The Goal is to Become a Gold Spoon so I need to be Completely Invulnerable","rating":9.2,"link":"https://www.mangago.me/read-manga/the_goal_is_to_become_a_gold_spoon_so_i_need_to_be_completely_invulnerable/"},{"title":"This Song Only For You","rating":9.2,"link":"https://www.mangago.me/read-manga/this_song_only_for_you/"},{"title":"Perfect Mine","rating":9.2,"link":"https://www.mangago.me/read-manga/perfect_mine/"},{"title":"The Villain's Savior","rating":9.2,"link":"https://www.mangago.me/read-manga/the_villain_s_savior/"},{"title":"Virtues of the Villainess","rating":9.2,"link":"https://www.mangago.me/read-manga/virtues_of_the_villainess/"},{"title":"I Became the Younger Sister of a Regretful Obsessive Male Lead","rating":9.2,"link":"https://www.mangago.me/read-manga/i_became_the_younger_sister_of_a_regretful_obsessive_male_lead/"},{"title":"The Fake Princess' OP Bunny","rating":9.2,"link":"https://www.mangago.me/read-manga/the_fake_princess_op_bunny/"},{"title":"Nice to Meet You","rating":9.2,"link":"https://www.mangago.me/read-manga/nice_to_meet_you/"},{"title":"Your Majesty, Please Don't Kill Me Again","rating":9.2,"link":"https://www.mangago.me/read-manga/your_majesty_please_don_t_kill_me_again/"},{"title":"The Reason Why Ophelia Can’t Get Away From The Duke","rating":9.1,"link":"https://www.mangago.me/read-manga/the_reason_why_ophelia_can_t_get_away_from_the_duke/"},{"title":"Change of Seasons / Between Seasons","rating":9,"link":"https://www.mangago.me/read-manga/change_of_seasons_between_seasons/"},{"title":"A river of hope","rating":8.9,"link":"https://www.mangago.me/read-manga/a_river_of_hope/"},{"title":"Good Morning, Billionaire Wife","rating":8.9,"link":"https://www.mangago.me/read-manga/good_morning_billionaire_wife/"},{"title":"Nan Shen Meng Bao Yi Guo Duan","rating":8.8,"link":"https://www.mangago.me/read-manga/nan_shen_meng_bao_yi_guo_duan/"},{"title":"I'm a Villainess But I Became a Mother","rating":8.8,"link":"https://www.mangago.me/read-manga/i_m_a_villainess_but_i_became_a_mother/"},{"title":"Princess of Doom","rating":8.8,"link":"https://www.mangago.me/read-manga/princess_of_doom/"},{"title":"Mia","rating":8.8,"link":"https://www.mangago.me/read-manga/mia/"},{"title":"The Elegant Sea of Savagery","rating":8.8,"link":"https://www.mangago.me/read-manga/the_elegant_sea_of_savagery/"},{"title":"Pregnant Wife, One Plus One","rating":8.7,"link":"https://www.mangago.me/read-manga/pregnant_wife_one_plus_one/"},{"title":"Head Over Heels","rating":8.5,"link":"https://www.mangago.me/read-manga/head_over_heels/"}]