[{"title":"Erotic Fairy Tales: The Little Mermaid","rating":8.6,"link":"https://www.mangago.me/read-manga/erotic_fairy_tales_the_little_mermaid/"},{"title":"Honey X Honey Drops","rating":8.3,"link":"https://www.mangago.me/read-manga/honey_x_honey_drops/"},{"title":"Chou yo Hana yo","rating":8.5,"link":"https://www.mangago.me/read-manga/chou_yo_hana_yo/"},{"title":"Hapi Mari","rating":9.1,"link":"https://www.mangago.me/read-manga/hapi_mari/"},{"title":"Midnight Secretary","rating":8.9,"link":"https://www.mangago.me/read-manga/midnight_secretary/"},{"title":"Boku ni Natta Watashi","rating":8.2,"link":"https://www.mangago.me/read-manga/boku_ni_natta_watashi/"},{"title":"Toy Complex","rating":9.2,"link":"https://www.mangago.me/read-manga/toy_complex/"},{"title":"Kiss de Fusaide, Bare naide.","rating":9.3,"link":"https://www.mangago.me/read-manga/kiss_de_fusaide_bare_naide/"},{"title":"Velvet Kiss","rating":8.4,"link":"https://www.mangago.me/read-manga/velvet_kiss/"},{"title":"Houkago, Seifuku o Nui de","rating":7.1,"link":"https://www.mangago.me/read-manga/houkago_seifuku_o_nui_de/"},{"title":"Aishite Kudasai, Sensei","rating":6.9,"link":"https://www.mangago.me/read-manga/aishite_kudasai_sensei/"},{"title":"JK's Tragic Isekai Reincarnation as the Villainess ~But My Precious Side Character!","rating":7.8,"link":"https://www.mangago.me/read-manga/jk_s_tragic_isekai_reincarnation_as_the_villainess_but_my_precious_side_character/"},{"title":"Ore Janee to Damena Kuse ni ~ Kono Otoko, Aishikata mo Chou Ichiryuu","rating":8.7,"link":"https://www.mangago.me/read-manga/ore_janee_to_damena_kuse_ni_kono_otoko_aishikata_mo_chou_ichiryuu/"}]