[{"title":"Coffee & Vanilla","rating":9.2,"link":"https://www.mangago.me/read-manga/coffee_vanilla/"},{"title":"Kaichou-sama Ga Fiance De","rating":8.5,"link":"https://www.mangago.me/read-manga/kaichou_sama_ga_fiance_de/"},{"title":"Light & Shadow","rating":9.6,"link":"https://www.mangago.me/read-manga/light_shadow/"},{"title":"Cigarette Kiss A Smoking Area Love Story","rating":8.1,"link":"https://www.mangago.me/read-manga/cigarette_kiss_a_smoking_area_love_story/"},{"title":"Mitsu Aji Blood","rating":8.6,"link":"https://www.mangago.me/read-manga/mitsu_aji_blood/"},{"title":"Mr. Cinderella","rating":8.9,"link":"https://www.mangago.me/read-manga/mr_cinderella/"},{"title":"My Housekeeper's a Boy!?","rating":8.7,"link":"https://www.mangago.me/read-manga/my_housekeeper_s_a_boy/"},{"title":"Totsuzen Desu ga, Ashita Kekkon Shimasu","rating":9.2,"link":"https://www.mangago.me/read-manga/totsuzen_desu_ga_ashita_kekkon_shimasu/"},{"title":"Shingeki no Eroko-san","rating":9.1,"link":"https://www.mangago.me/read-manga/shingeki_no_eroko_san/"},{"title":"Unwanted Wedding","rating":7.4,"link":"https://www.mangago.me/read-manga/unwanted_wedding/"},{"title":"My Cute Bedfellow","rating":8.7,"link":"https://www.mangago.me/read-manga/my_cute_bedfellow/"},{"title":"Shitsuren Misui","rating":8.8,"link":"https://www.mangago.me/read-manga/shitsuren_misui/"},{"title":"Negattari Kanattari","rating":8.4,"link":"https://www.mangago.me/read-manga/negattari_kanattari/"},{"title":"Yanagihara-kun wa Sex Izonshou","rating":8.8,"link":"https://www.mangago.me/read-manga/yanagihara_kun_wa_sex_izonshou/"},{"title":"Daylight","rating":8,"link":"https://www.mangago.me/read-manga/daylight/"},{"title":"Anata Dake no Koibana","rating":7.1,"link":"https://www.mangago.me/read-manga/anata_dake_no_koibana/"},{"title":"Migawari Hanayome no Konzen Choukyou","rating":7.1,"link":"https://www.mangago.me/read-manga/migawari_hanayome_no_konzen_choukyou/"},{"title":"What's going on?","rating":9.1,"link":"https://www.mangago.me/read-manga/what_s_going_on/"},{"title":"Acchi no Renshuu Hajimemashita","rating":9,"link":"https://www.mangago.me/read-manga/acchi_no_renshuu_hajimemashita/"},{"title":"Marika-chan to Yasashii Koi no Dorei","rating":9,"link":"https://www.mangago.me/read-manga/marika_chan_to_yasashii_koi_no_dorei/"},{"title":"Kare to Kanojo ha XX dekinai","rating":8.7,"link":"https://www.mangago.me/read-manga/kare_to_kanojo_ha_xx_dekinai/"},{"title":"Takanozomi no koishite warui ka yo","rating":8.5,"link":"https://www.mangago.me/read-manga/takanozomi_no_koishite_warui_ka_yo/"},{"title":"Oshiete yaruyo mitaina Kimochiii Koto -Kouhai PariPi ha Moto Ninki Doujin Sakka-","rating":9,"link":"https://www.mangago.me/read-manga/oshiete_yaruyo_manga_mitaina_kimochiii_koto_kouhai_paripi_ha_moto_ninki_doujin_sakka/"},{"title":"Coffee & Vanilla Black","rating":9.3,"link":"https://www.mangago.me/read-manga/coffee_vanilla_black/"},{"title":"Amaku Nureru Uso Kekkon Toiu na no Fukushu","rating":8.6,"link":"https://www.mangago.me/read-manga/amaku_nureru_uso_kekkon_toiu_na_no_fukushu/"},{"title":"Illicit Night with the Greek","rating":6.9,"link":"https://www.mangago.me/read-manga/illicit_night_with_the_greek/"},{"title":"Tensei shitara Maou-sama ni Dekiai saremashita","rating":9.1,"link":"https://www.mangago.me/read-manga/tensei_shitara_maou_sama_ni_dekiai_saremashita/"},{"title":"Majo no Biyaku","rating":8.9,"link":"https://www.mangago.me/read-manga/majo_no_biyaku/"},{"title":"Gokukon ~Chou Dekiai Yakuza to Keiyaku Kekkon!?~","rating":8.8,"link":"https://www.mangago.me/read-manga/gokukon_chou_dekiai_yakuza_to_keiyaku_kekkon/"},{"title":"Bite maker","rating":8.8,"link":"https://www.mangago.me/read-manga/bite_maker/"},{"title":"Hime to Mahou Tsukai","rating":9.1,"link":"https://www.mangago.me/read-manga/hime_to_mahou_tsukai/"},{"title":"The Sheikh's shock child","rating":8,"link":"https://www.mangago.me/read-manga/the_sheikh_s_shock_child/"},{"title":"Sabaku no Ouji to Unmei no Hanayome","rating":7.9,"link":"https://www.mangago.me/read-manga/sabaku_no_ouji_to_unmei_no_hanayome/"},{"title":"Dekinai Futari","rating":9.2,"link":"https://www.mangago.me/read-manga/dekinai_futari/"},{"title":"The Moon On The Cliff","rating":9.3,"link":"https://www.mangago.me/read-manga/the_moon_on_the_cliff_19/"},{"title":"Onimiya-sensei No Kisu Ni Wa Sakaraenai","rating":8.4,"link":"https://www.mangago.me/read-manga/onimiya_sensei_no_kisu_ni_wa_sakaraenai/"},{"title":"The Court Lady","rating":8.9,"link":"https://www.mangago.me/read-manga/the_court_lady/"},{"title":"Kisarazu kun no XX ga mitai","rating":9,"link":"https://www.mangago.me/read-manga/kisarazu_kun_no_xx_ga_mitai/"},{"title":"MotokareâRetry","rating":7.9,"link":"https://www.mangago.me/read-manga/motokare_retry/"},{"title":"Akuyaku Reijo to Shite Shikei Senkoku sa Retara dai Akuma ni Mede Raremashita","rating":8.2,"link":"https://www.mangago.me/read-manga/akuyaku_reijo_to_shite_shikei_senkoku_sa_retara_dai_akuma_ni_mede_raremashita/"},{"title":"Saikou no Numakon Watashitachi no Kankei ha Hutsuu ja nai","rating":8.7,"link":"https://www.mangago.me/read-manga/saikou_no_numakon_watashitachi_no_kankei_ha_hutsuu_ja_nai/"},{"title":"Vicarious Lover","rating":9,"link":"https://www.mangago.me/read-manga/vicarious_lover/"},{"title":"Gokudou no Otoko, Kaimasu.","rating":9,"link":"https://www.mangago.me/read-manga/gokudou_no_otoko_kaimasu/"},{"title":"Sensei no Himitsu ~Kimi no ♡♡ ga Suki~","rating":8.3,"link":"https://www.mangago.me/read-manga/sensei_no_himitsu_kimi_no_ga_suki/"},{"title":"I Love You as You Are, Strong and Ambitious","rating":8.8,"link":"https://www.mangago.me/read-manga/i_love_you_as_you_are_strong_and_ambitious/"},{"title":"Dochirano Kuzu o Aishimasuka?","rating":8.1,"link":"https://www.mangago.me/read-manga/dochirano_kuzu_o_aishimasuka/"},{"title":"The Doting Tyrant","rating":8.8,"link":"https://www.mangago.me/read-manga/the_doting_tyrant/"},{"title":"The Old Man And The Maiden","rating":8.4,"link":"https://www.mangago.me/read-manga/the_old_man_and_the_maiden/"},{"title":"Sodatete, Kowasu","rating":7.5,"link":"https://www.mangago.me/read-manga/sodatete_kowasu/"},{"title":"JK's Tragic Isekai Reincarnation as the Villainess ~But My Precious Side Character!","rating":7.8,"link":"https://www.mangago.me/read-manga/jk_s_tragic_isekai_reincarnation_as_the_villainess_but_my_precious_side_character/"},{"title":"Kind and Sadistic ~ My Husband's Special Brand of Love ~","rating":8.4,"link":"https://www.mangago.me/read-manga/kind_and_sadistic_my_husband_s_special_brand_of_love/"},{"title":"Kiss wa Oboeta kara, \"Sono Saki\" wo Oshiete?","rating":8.2,"link":"https://www.mangago.me/read-manga/kiss_wa_oboeta_kara_sono_saki_wo_oshiete/"},{"title":"Totsuki Tooka no Setsuai Fuufu Jijou","rating":8.8,"link":"https://www.mangago.me/read-manga/totsuki_tooka_no_setsuai_fuufu_jijou/"},{"title":"Can You Be Satisfied Just to Sleep With Me?","rating":7.1,"link":"https://www.mangago.me/read-manga/can_you_be_satisfied_just_to_sleep_with_me/"},{"title":"Densiban Haraguro Onzôsi Ga Iziwaru Desu","rating":8.1,"link":"https://www.mangago.me/read-manga/densiban_haraguro_onz_si_ga_iziwaru_desu/"}]